file_golem/__init__.py
file_golem/_file_io_helper.py
file_golem/class_handler.py
file_golem/config_datatype.py
file_golem/file_datatypes.py
file_golem/file_io_object.py
file_golem-0.1.13.dist-info/METADATA
file_golem-0.1.13.dist-info/WHEEL
file_golem-0.1.13.dist-info/top_level.txt
file_golem-0.1.13.dist-info/RECORD
