Metadata-Version: 2.4
Name: file_golem
Version: 0.1.13
Summary: A file i/o utility to handle complex projects with multiple datasets, project locations and calls to 3rd party codebases.
Home-page: https://github.com/CameronBraunstein/file_golem
Author: Cameron Braunstein
Author-email: your.email@example.com
Classifier: Programming Language :: Python :: 3
Classifier: License :: OSI Approved :: MIT License
Classifier: Operating System :: OS Independent
Requires-Python: >=3.6
Requires-Dist: omegaconf
Requires-Dist: filelock
Dynamic: author
Dynamic: author-email
Dynamic: classifier
Dynamic: description
Dynamic: description-content-type
Dynamic: home-page
Dynamic: requires-dist
Dynamic: requires-python
Dynamic: summary
